MANIFEST.in
README.md
README.txt
setup.cfg
setup.py
ssh_manage_api/__init__.py
ssh_manage_api/__main__.py
ssh_manage_api/commands.py
ssh_manage_api/helpers.py
ssh_manage_api/webapi.py
ssh_manage_api.egg-info/PKG-INFO
ssh_manage_api.egg-info/SOURCES.txt
ssh_manage_api.egg-info/dependency_links.txt
ssh_manage_api.egg-info/requires.txt
ssh_manage_api.egg-info/top_level.txt