Metadata-Version: 1.1
Name: ssh-manage-api
Version: 2.2
Summary: simple batch manage ssh_keys and support web api
Home-page: https://github.com/rfyiamcool
Author: ruifengyun
Author-email: rfyiamcool@163.com
License: UNKNOWN
Platform: UNKNOWN
Classifier: Operating System :: Unix
Classifier: Programming Language :: Python :: 2
Classifier: Programming Language :: Python :: 2.7
Classifier: Programming Language :: Python :: 3
Classifier: Programming Language :: Python :: 3.3
